setup.cfg
setup.py
classier/__init__.py
classier.egg-info/PKG-INFO
classier.egg-info/SOURCES.txt
classier.egg-info/dependency_links.txt
classier.egg-info/top_level.txt
classier/decorators/__init__.py
classier/decorators/has_state_decorator/__init__.py
classier/decorators/has_state_decorator/_tests.py
classier/decorators/has_state_decorator/has_state.py
classier/decorators/has_state_decorator/_add_magic_methods/__init__.py
classier/decorators/has_state_decorator/_add_magic_methods/_add__delitem__.py
classier/decorators/has_state_decorator/_add_magic_methods/_add__eq__.py
classier/decorators/has_state_decorator/_add_magic_methods/_add__getitem__.py
classier/decorators/has_state_decorator/_add_magic_methods/_add__init__.py
classier/decorators/has_state_decorator/_add_magic_methods/_add__len__.py
classier/decorators/has_state_decorator/_add_magic_methods/_add__setitem__.py
classier/decorators/has_state_decorator/_add_magic_methods/_add__str__.py
classier/decorators/has_state_decorator/_add_state_methods/__init__.py
classier/decorators/has_state_decorator/_add_state_methods/_add_del_state.py
classier/decorators/has_state_decorator/_add_state_methods/_add_does_state_exist.py
classier/decorators/has_state_decorator/_add_state_methods/_add_from_pointer.py
classier/decorators/has_state_decorator/_add_state_methods/_add_get_state.py
classier/decorators/has_state_decorator/_add_state_methods/_add_get_state_path.py
classier/decorators/has_state_decorator/_add_state_methods/_add_save_state.py
classier/decorators/has_state_decorator/_add_state_methods/_add_update_state.py
classier/decorators/has_state_decorator/options/ATTRIBUTE_OPTIONS.py
classier/decorators/has_state_decorator/options/MAGIC_METHODS_OPTIONS.py
classier/decorators/has_state_decorator/options/METHOD_OPTIONS.py
classier/decorators/has_state_decorator/options/__init__.py
classier/locks/AbstractLock.py
classier/locks/LockNameSpace.py
classier/locks/LockRecord.py
classier/locks/ReadExclusiveLock.py
classier/locks/ReadLock.py
classier/locks/WriteLock.py
classier/locks/__init__.py
classier/locks/_tests.py
classier/objects/ClassMarker.py
