Metadata-Version: 1.1
Name: classier
Version: 0.0.8
Summary: Make your classes classier.
Home-page: https://github.com/ozgeneral/classier
Author: Ozgen Eren
Author-email: ozgeneral@gmail.com
License: MIT
Download-URL: https://github.com/ozgeneral/classier/archive/0.0.8.tar.gz
Keywords: classier,utils,convenience
Platform: UNKNOWN
Classifier: Development Status :: 3 - Alpha
Classifier: Intended Audience :: Developers
Classifier: Topic :: Software Development :: Build Tools
Classifier: License :: OSI Approved :: MIT License
Classifier: Programming Language :: Python :: 3
Classifier: Programming Language :: Python :: 3.7
